mcmod_resize/__init__.py
mcmod_resize/cli.py
mcmod_resize/main_.py
mcmod_resize-0.1.1.dist-info/LICENSE
mcmod_resize-0.1.1.dist-info/METADATA
mcmod_resize-0.1.1.dist-info/WHEEL
mcmod_resize-0.1.1.dist-info/entry_points.txt
mcmod_resize-0.1.1.dist-info/top_level.txt
mcmod_resize-0.1.1.dist-info/RECORD
